slipcover/__init__.py
slipcover/__main__.py
slipcover/branch.py
slipcover/bytecode.py
slipcover/fuzz.py
slipcover/importer.py
slipcover/schemas.py
slipcover/slipcover.py
slipcover/version.py
slipcover/xmlreport.py
slipcover-1.0.17.dist-info/licenses/LICENSE
slipcover-1.0.17.dist-info/METADATA
slipcover-1.0.17.dist-info/WHEEL
slipcover-1.0.17.dist-info/entry_points.txt
slipcover-1.0.17.dist-info/top_level.txt
slipcover-1.0.17.dist-info/RECORD
