Metadata-Version: 2.1
Name: slipcover
Version: 1.0.17
Summary: Near Zero-Overhead Python Code Coverage
Author-email: Juan Altmayer Pizzorno <juan@altmayer.com>, Emery Berger <emery.berger@gmail.com>
Project-URL: Homepage, https://github.com/plasma-umass/slipcover
Project-URL: Repository, https://github.com/plasma-umass/slipcover
Keywords: coverage,testing
Classifier: Programming Language :: Python :: 3.8
Classifier: Programming Language :: Python :: 3.9
Classifier: Programming Language :: Python :: 3.10
Classifier: Programming Language :: Python :: 3.11
Classifier: Programming Language :: Python :: 3.12
Classifier: Programming Language :: Python :: 3.13
Classifier: Programming Language :: Python :: 3.14
Classifier: License :: OSI Approved :: Apache Software License
Classifier: Operating System :: POSIX :: Linux
Classifier: Operating System :: MacOS :: MacOS X
Classifier: Operating System :: Microsoft :: Windows :: Windows 10
Requires-Python: <3.15,>=3.8
License-File: LICENSE
Requires-Dist: tabulate
Provides-Extra: test
Requires-Dist: pytest; extra == "test"
Requires-Dist: pytest-forked; extra == "test"
